odoo/addons/ssi_general_audit_worksheet_understanding_entity/README.rst
odoo/addons/ssi_general_audit_worksheet_understanding_entity/__init__.py
odoo/addons/ssi_general_audit_worksheet_understanding_entity/__manifest__.py
odoo/addons/ssi_general_audit_worksheet_understanding_entity/menu.xml
odoo/addons/ssi_general_audit_worksheet_understanding_entity/data/general_audit_worksheet_type_data.xml
odoo/addons/ssi_general_audit_worksheet_understanding_entity/data/approval_template/general_audit_ws_a13a30e.xml
odoo/addons/ssi_general_audit_worksheet_understanding_entity/data/approval_template/general_audit_ws_a604795.xml
odoo/addons/ssi_general_audit_worksheet_understanding_entity/data/approval_template/general_audit_ws_ae11f7e.xml
odoo/addons/ssi_general_audit_worksheet_understanding_entity/data/approval_template/general_audit_ws_bdcdfc5.xml
odoo/addons/ssi_general_audit_worksheet_understanding_entity/data/approval_template/general_audit_ws_c0d0898.xml
odoo/addons/ssi_general_audit_worksheet_understanding_entity/data/approval_template/general_audit_ws_c0e0eec.xml
odoo/addons/ssi_general_audit_worksheet_understanding_entity/data/approval_template/general_audit_ws_e78a3c6.xml
odoo/addons/ssi_general_audit_worksheet_understanding_entity/data/approval_template/general_audit_ws_f6a227.xml
odoo/addons/ssi_general_audit_worksheet_understanding_entity/data/ir_sequence/general_audit_ws_a13a30e.xml
odoo/addons/ssi_general_audit_worksheet_understanding_entity/data/ir_sequence/general_audit_ws_a604795.xml
odoo/addons/ssi_general_audit_worksheet_understanding_entity/data/ir_sequence/general_audit_ws_ae11f7e.xml
odoo/addons/ssi_general_audit_worksheet_understanding_entity/data/ir_sequence/general_audit_ws_bdcdfc5.xml
odoo/addons/ssi_general_audit_worksheet_understanding_entity/data/ir_sequence/general_audit_ws_c0d0898.xml
odoo/addons/ssi_general_audit_worksheet_understanding_entity/data/ir_sequence/general_audit_ws_c0e0eec.xml
odoo14_addon_ssi_general_audit_worksheet_understanding_entity-14.0.1.10.0.dist-info/METADATA
odoo14_addon_ssi_general_audit_worksheet_understanding_entity-14.0.1.10.0.dist-info/WHEEL
odoo14_addon_ssi_general_audit_worksheet_understanding_entity-14.0.1.10.0.dist-info/top_level.txt
odoo14_addon_ssi_general_audit_worksheet_understanding_entity-14.0.1.10.0.dist-info/RECORD
